{
  "id": "@hugeicons/mcp-server",
  "name": "@hugeicons/mcp-server",
  "display_name": "Hugeicons MCP Server",
  "version": null,
  "description": "Integrate Hugeicons seamlessly into your applications. Discover icons, access platform-specific usage instructions, and enhance your projects with comprehensive documentation and examples.",
  "icon_url": "https://icons.duckduckgo.com/ip3/hugeicons.com.ico",
  "repository_url": null,
  "status": "active",
  "published_at": null,
  "tools": [
    {
      "name": "list_icons",
      "description": "Get a list of all available Hugeicons icons",
      "inputSchema": {
        "type": "object",
        "required": [],
        "properties": {}
      }
    },
    {
      "name": "search_icons",
      "description": "Search for icons by name or tags. Use commas to search for multiple icons (e.g. 'home, notification, settings')",
      "inputSchema": {
        "type": "object",
        "required": [
          "query"
        ],
        "properties": {
          "query": {
            "type": "string",
            "description": "Search query to find relevant icons. Separate multiple searches with commas"
          }
        }
      }
    },
    {
      "name": "get_platform_usage",
      "description": "Get platform-specific usage instructions for Hugeicons",
      "inputSchema": {
        "type": "object",
        "required": [
          "platform"
        ],
        "properties": {
          "platform": {
            "enum": [
              "react",
              "vue",
              "angular",
              "svelte",
              "react-native",
              "flutter",
              "html"
            ],
            "type": "string",
            "description": "Platform name (react, vue, angular, svelte, react-native, flutter, html)"
          }
        }
      }
    },
    {
      "name": "get_icon_glyphs",
      "description": "Get all glyphs (unicode characters) for a specific icon across all available styles",
      "inputSchema": {
        "type": "object",
        "required": [
          "icon_name"
        ],
        "properties": {
          "icon_name": {
            "type": "string",
            "description": "The name of the icon (e.g., 'home-01', 'notification-02')"
          }
        }
      }
    },
    {
      "name": "get_icon_glyph_by_style",
      "description": "Get the glyph (unicode character) for a specific icon with a particular style",
      "inputSchema": {
        "type": "object",
        "required": [
          "icon_name",
          "style"
        ],
        "properties": {
          "style": {
            "enum": [
              "bulk-rounded",
              "duotone-rounded",
              "solid-rounded",
              "solid-sharp",
              "solid-standard",
              "stroke-rounded",
              "stroke-sharp",
              "stroke-standard",
              "twotone-rounded"
            ],
            "type": "string",
            "description": "The icon style"
          },
          "icon_name": {
            "type": "string",
            "description": "The name of the icon (e.g., 'home-01', 'notification-02')"
          }
        }
      }
    }
  ],
  "tool_count": 5,
  "prompts": [],
  "resources": [],
  "remote_endpoint": null,
  "packages": [],
  "sources": [
    "smithery"
  ],
  "primary_source": "smithery",
  "is_latest": true,
  "verified": false,
  "use_count": 0,
  "has_remote": false,
  "has_tools": true,
  "tool_names": [
    "list_icons",
    "search_icons",
    "get_platform_usage",
    "get_icon_glyphs",
    "get_icon_glyph_by_style"
  ]
}