{
  "id": "@puremd/puremd-mcp",
  "name": "@puremd/puremd-mcp",
  "display_name": "pure.md MCP server",
  "version": null,
  "description": "Access web content in markdown format reliably and efficiently. Unblock web pages and search the web seamlessly, enhancing your agents' capabilities. Integrate with your scripts and applications to leverage markdown delivery like a CDN.",
  "icon_url": "https://icons.duckduckgo.com/ip3/pure.md.ico",
  "repository_url": null,
  "status": "active",
  "published_at": null,
  "tools": [
    {
      "name": "unblock-url",
      "inputSchema": {
        "type": "object",
        "$schema": "http://json-schema.org/draft-07/schema#",
        "required": [
          "url"
        ],
        "properties": {
          "url": {
            "type": "string"
          }
        },
        "additionalProperties": false
      }
    },
    {
      "name": "search-web",
      "inputSchema": {
        "type": "object",
        "$schema": "http://json-schema.org/draft-07/schema#",
        "required": [
          "query"
        ],
        "properties": {
          "query": {
            "type": "string"
          }
        },
        "additionalProperties": false
      }
    }
  ],
  "tool_count": 2,
  "prompts": [],
  "resources": [],
  "remote_endpoint": null,
  "packages": [],
  "sources": [
    "smithery"
  ],
  "primary_source": "smithery",
  "is_latest": true,
  "verified": false,
  "use_count": 0,
  "has_remote": false,
  "has_tools": true,
  "tool_names": [
    "unblock-url",
    "search-web"
  ]
}