{
  "id": "@vinnyang/axe-scanner-mcp",
  "name": "@vinnyang/axe-scanner-mcp",
  "display_name": "axe-scanner-mcp",
  "version": null,
  "description": "A standalone Model Context Protocol server that runs axe accessibility scans for a supplied URL using Playwright.",
  "icon_url": "https://icons.duckduckgo.com/ip3/github.com.ico",
  "repository_url": null,
  "status": "active",
  "published_at": null,
  "tools": [],
  "tool_count": 0,
  "prompts": [],
  "resources": [],
  "remote_endpoint": null,
  "packages": [],
  "sources": [
    "smithery"
  ],
  "primary_source": "smithery",
  "is_latest": true,
  "verified": false,
  "use_count": 0,
  "has_remote": false,
  "has_tools": false,
  "tool_names": []
}