{
  "id": "ai.smithery/MisterSandFR-supabase-mcp-selfhosted",
  "name": "ai.smithery/MisterSandFR-supabase-mcp-selfhosted",
  "display_name": "ai.smithery/MisterSandFR-supabase-mcp-selfhosted",
  "version": "1.14.1",
  "description": "Manage Supabase projects end to end across database, auth, storage, realtime, and migrations. Moni\u2026",
  "icon_url": null,
  "repository_url": "https://github.com/MisterSandFR/Supabase-MCP-SelfHosted",
  "status": "active",
  "published_at": "2025-09-18T14:42:06.197815Z",
  "tools": [],
  "tool_count": 0,
  "prompts": [],
  "resources": [],
  "remote_endpoint": "https://server.smithery.ai/@MisterSandFR/supabase-mcp-selfhosted/mcp",
  "packages": [],
  "sources": [
    "official"
  ],
  "primary_source": "official",
  "is_latest": true,
  "verified": false,
  "use_count": 0,
  "has_remote": true,
  "has_tools": false,
  "tool_names": []
}