{
  "id": "ai.smithery/IndianAppGuy-magicslide-mcp",
  "name": "ai.smithery/IndianAppGuy-magicslide-mcp",
  "display_name": "ai.smithery/IndianAppGuy-magicslide-mcp",
  "version": "1.0.0",
  "description": "Generate professional PowerPoint presentations from text, YouTube videos, or structured JSON data.\u2026",
  "icon_url": null,
  "repository_url": null,
  "status": "active",
  "published_at": "2025-10-08T05:29:39.856257Z",
  "tools": [],
  "tool_count": 0,
  "prompts": [],
  "resources": [],
  "remote_endpoint": "https://server.smithery.ai/@IndianAppGuy/magicslide-mcp/mcp",
  "packages": [],
  "sources": [
    "official"
  ],
  "primary_source": "official",
  "is_latest": true,
  "verified": false,
  "use_count": 0,
  "has_remote": true,
  "has_tools": false,
  "tool_names": []
}