{
  "id": "io.github.Lyellr88/marm-mcp-server",
  "name": "io.github.Lyellr88/marm-mcp-server",
  "display_name": "io.github.Lyellr88/marm-mcp-server",
  "version": "2.2.5",
  "description": "Universal MCP Server with advanced AI memory capabilities and semantic search.",
  "icon_url": null,
  "repository_url": "https://github.com/Lyellr88/MARM-Systems",
  "status": "active",
  "published_at": "2025-09-23T06:50:35.598481Z",
  "tools": [],
  "tool_count": 0,
  "prompts": [],
  "resources": [],
  "remote_endpoint": null,
  "packages": [
    {
      "registryType": "pypi",
      "identifier": "marm-mcp-server",
      "version": "2.2.5",
      "transport": {
        "type": "stdio"
      }
    },
    {
      "registryType": "oci",
      "identifier": "docker.io/lyellr88/marm-mcp-server:2.2.5",
      "transport": {
        "type": "stdio"
      }
    }
  ],
  "sources": [
    "official"
  ],
  "primary_source": "official",
  "is_latest": true,
  "verified": false,
  "use_count": 0,
  "has_remote": false,
  "has_tools": false,
  "tool_names": []
}