{
  "qualifiedName": "@emmanuel/ll8",
  "displayName": "Zuplo",
  "description": "Connect to Zuplo to perform tasks directly from your workspace. Automate routine operations and fetch relevant data without switching tools. Save time and keep your workflow in one place.",
  "iconUrl": null,
  "remote": true,
  "deploymentUrl": "https://server.smithery.ai/@emmanuel/ll8",
  "connections": [
    {
      "type": "http",
      "deploymentUrl": "https://server.smithery.ai/@emmanuel/ll8/mcp",
      "configSchema": {}
    }
  ],
  "security": null,
  "tools": [],
  "_sync": {
    "fetched_at": "2026-01-04T13:22:37.674274+00:00",
    "source": "smithery"
  }
}