{
  "qualifiedName": "@alxspiker/mcp-server-ftp",
  "displayName": "FTP Access Server",
  "description": "Interact with FTP servers seamlessly. List directories, upload and download files, and manage your FTP resources effortlessly using natural language commands.",
  "iconUrl": null,
  "remote": false,
  "deploymentUrl": null,
  "connections": [
    {
      "type": "stdio",
      "bundleUrl": "https://backend.smithery.ai/storage/v1/object/public/bundles/@alxspiker/mcp-server-ftp/server.mcpb",
      "runtime": "node",
      "configSchema": {
        "type": "object",
        "required": [
          "ftpHost",
          "ftpPort",
          "ftpUser",
          "ftpPassword",
          "ftpSecure"
        ],
        "properties": {
          "ftpHost": {
            "type": "string",
            "default": "localhost",
            "description": "FTP server hostname or IP address"
          },
          "ftpPort": {
            "type": "number",
            "default": 21,
            "description": "FTP server port"
          },
          "ftpUser": {
            "type": "string",
            "default": "anonymous",
            "description": "FTP username"
          },
          "ftpSecure": {
            "type": "boolean",
            "default": false,
            "description": "Use secure FTP (FTPS)"
          },
          "ftpPassword": {
            "type": "string",
            "default": "",
            "description": "FTP password"
          }
        }
      }
    }
  ],
  "security": {
    "scanPassed": true
  },
  "tools": [
    {
      "name": "list-directory",
      "description": "List contents of an FTP directory",
      "inputSchema": {
        "type": "object",
        "$schema": "http://json-schema.org/draft-07/schema#",
        "required": [
          "remotePath"
        ],
        "properties": {
          "remotePath": {
            "type": "string",
            "description": "Path of the directory on the FTP server"
          }
        },
        "additionalProperties": false
      }
    },
    {
      "name": "download-file",
      "description": "Download a file from the FTP server",
      "inputSchema": {
        "type": "object",
        "$schema": "http://json-schema.org/draft-07/schema#",
        "required": [
          "remotePath"
        ],
        "properties": {
          "remotePath": {
            "type": "string",
            "description": "Path of the file on the FTP server"
          }
        },
        "additionalProperties": false
      }
    },
    {
      "name": "upload-file",
      "description": "Upload a file to the FTP server",
      "inputSchema": {
        "type": "object",
        "$schema": "http://json-schema.org/draft-07/schema#",
        "required": [
          "remotePath",
          "content"
        ],
        "properties": {
          "content": {
            "type": "string",
            "description": "Content to upload to the file"
          },
          "remotePath": {
            "type": "string",
            "description": "Destination path on the FTP server"
          }
        },
        "additionalProperties": false
      }
    },
    {
      "name": "create-directory",
      "description": "Create a new directory on the FTP server",
      "inputSchema": {
        "type": "object",
        "$schema": "http://json-schema.org/draft-07/schema#",
        "required": [
          "remotePath"
        ],
        "properties": {
          "remotePath": {
            "type": "string",
            "description": "Path of the directory to create"
          }
        },
        "additionalProperties": false
      }
    },
    {
      "name": "delete-file",
      "description": "Delete a file from the FTP server",
      "inputSchema": {
        "type": "object",
        "$schema": "http://json-schema.org/draft-07/schema#",
        "required": [
          "remotePath"
        ],
        "properties": {
          "remotePath": {
            "type": "string",
            "description": "Path of the file to delete"
          }
        },
        "additionalProperties": false
      }
    },
    {
      "name": "delete-directory",
      "description": "Delete a directory from the FTP server",
      "inputSchema": {
        "type": "object",
        "$schema": "http://json-schema.org/draft-07/schema#",
        "required": [
          "remotePath"
        ],
        "properties": {
          "remotePath": {
            "type": "string",
            "description": "Path of the directory to delete"
          }
        },
        "additionalProperties": false
      }
    }
  ],
  "_sync": {
    "fetched_at": "2026-01-04T13:53:18.286964+00:00",
    "source": "smithery"
  }
}