{
  "server": {
    "$schema": "https://static.modelcontextprotocol.io/schemas/2025-10-17/server.schema.json",
    "name": "io.github.imbenrabi/financial-modeling-prep-mcp-server",
    "description": "MCP server for Financial Modeling Prep API with 250+ financial data tools",
    "title": "Financial Modeling Prep MCP Server",
    "repository": {
      "url": "https://github.com/imbenrabi/Financial-Modeling-Prep-MCP-Server",
      "source": "github"
    },
    "version": "2.5.3",
    "websiteUrl": "https://github.com/imbenrabi/Financial-Modeling-Prep-MCP-Server",
    "packages": [
      {
        "registryType": "npm",
        "registryBaseUrl": "https://registry.npmjs.org",
        "identifier": "financial-modeling-prep-mcp-server",
        "version": "2.5.3",
        "runtimeHint": "npx",
        "transport": {
          "type": "streamable-http",
          "url": "https://financial-modeling-prep-mcp-server-production.up.railway.app/mcp"
        },
        "packageArguments": [
          {
            "description": "Financial Modeling Prep API access token",
            "format": "string",
            "type": "named",
            "name": "--fmp-token"
          },
          {
            "description": "Port number for HTTP server mode",
            "format": "number",
            "type": "named",
            "name": "--port"
          },
          {
            "description": "Enable dynamic tool discovery mode",
            "format": "boolean",
            "type": "named",
            "name": "--dynamic-tool-discovery"
          },
          {
            "description": "Comma-separated list of tool sets to load",
            "format": "string",
            "type": "named",
            "name": "--fmp-tool-sets"
          }
        ],
        "environmentVariables": [
          {
            "description": "Financial Modeling Prep API access token",
            "format": "string",
            "isSecret": true,
            "name": "FMP_ACCESS_TOKEN"
          },
          {
            "description": "Port number for HTTP server mode",
            "format": "number",
            "name": "PORT"
          },
          {
            "description": "Enable dynamic tool discovery mode",
            "format": "boolean",
            "name": "DYNAMIC_TOOL_DISCOVERY"
          },
          {
            "description": "Comma-separated list of tool sets to load",
            "format": "string",
            "name": "FMP_TOOL_SETS"
          }
        ]
      }
    ]
  },
  "_meta": {
    "io.modelcontextprotocol.registry/official": {
      "status": "active",
      "publishedAt": "2025-12-06T13:18:36.03235Z",
      "updatedAt": "2025-12-06T13:18:36.03235Z",
      "isLatest": true
    }
  },
  "_sync": {
    "fetched_at": "2026-01-04T12:05:28.328970+00:00",
    "source": "registry.modelcontextprotocol.io"
  }
}