{
  "server": {
    "$schema": "https://static.modelcontextprotocol.io/schemas/2025-09-29/server.schema.json",
    "name": "io.github.cyanheads/pubmed-mcp-server",
    "description": "Comprehensive PubMed MCP Server to search, retrieve, and analyze biomedical literature from NCBI.",
    "repository": {
      "url": "https://github.com/cyanheads/pubmed-mcp-server",
      "source": "github"
    },
    "version": "1.4.4",
    "packages": [
      {
        "registryType": "npm",
        "registryBaseUrl": "https://registry.npmjs.org",
        "identifier": "@cyanheads/pubmed-mcp-server",
        "version": "1.4.4",
        "runtimeHint": "node",
        "transport": {
          "type": "stdio"
        },
        "packageArguments": [
          {
            "value": "dist/index.js",
            "type": "positional"
          }
        ],
        "environmentVariables": [
          {
            "description": "Specifies the transport mechanism for the server.",
            "isRequired": true,
            "format": "string",
            "default": "stdio",
            "name": "MCP_TRANSPORT_TYPE"
          },
          {
            "description": "Sets the minimum log level for output (e.g., 'debug', 'info', 'warn').",
            "format": "string",
            "default": "info",
            "name": "MCP_LOG_LEVEL"
          },
          {
            "description": "Your NCBI API key for higher rate limits.",
            "format": "string",
            "name": "NCBI_API_KEY"
          }
        ]
      },
      {
        "registryType": "npm",
        "registryBaseUrl": "https://registry.npmjs.org",
        "identifier": "@cyanheads/pubmed-mcp-server",
        "version": "1.4.4",
        "runtimeHint": "node",
        "transport": {
          "type": "streamable-http",
          "url": "http://localhost:3017/mcp"
        },
        "packageArguments": [
          {
            "value": "dist/index.js",
            "type": "positional"
          }
        ],
        "environmentVariables": [
          {
            "description": "Specifies the transport mechanism for the server.",
            "isRequired": true,
            "format": "string",
            "default": "http",
            "name": "MCP_TRANSPORT_TYPE"
          },
          {
            "description": "The host for the HTTP server.",
            "format": "string",
            "default": "localhost",
            "name": "MCP_HTTP_HOST"
          },
          {
            "description": "The port for the HTTP server.",
            "format": "string",
            "default": "3017",
            "name": "MCP_HTTP_PORT"
          },
          {
            "description": "The endpoint path for MCP requests.",
            "format": "string",
            "default": "/mcp",
            "name": "MCP_HTTP_ENDPOINT_PATH"
          },
          {
            "description": "Authentication mode: 'none', 'jwt', or 'oauth'.",
            "format": "string",
            "default": "none",
            "name": "MCP_AUTH_MODE"
          },
          {
            "description": "Sets the minimum log level (e.g., 'debug', 'info', 'warn').",
            "format": "string",
            "default": "info",
            "name": "MCP_LOG_LEVEL"
          },
          {
            "description": "Your NCBI API key for higher rate limits.",
            "format": "string",
            "name": "NCBI_API_KEY"
          }
        ]
      }
    ]
  },
  "_meta": {
    "io.modelcontextprotocol.registry/official": {
      "status": "active",
      "publishedAt": "2025-09-15T13:34:11.145839Z",
      "updatedAt": "2025-09-15T13:34:11.145839Z",
      "isLatest": false
    }
  },
  "_sync": {
    "fetched_at": "2026-01-04T12:05:27.219921+00:00",
    "source": "registry.modelcontextprotocol.io"
  }
}